{
  "search_by_text":
    [
      {
        "id": 1,
        "image_url": "https://picsum.photos/400/300/?random=1",
        "title": "test",
        "about": "Jeff & Jason & Irene was shit.",
        "tags": ["panda", "dog", "shit"]
      },
      {
        "id": 2,
        "image_url": "https://picsum.photos/400/300/?random=2",
        "title": "test",
        "about": "Jeff & Jason & Irene was shit.",
        "tags": ["panda", "dog", "shit"]
      },
      {
        "id": 3,
        "image_url": "https://picsum.photos/400/300/?random=3",
        "title": "test",
        "about": "Jeff & Jason & Irene was shit.",
        "tags": ["panda", "dog", "shit"]
      },
      {
        "id": 4,
        "image_url": "https://picsum.photos/600/300/?random=4",
        "title": "test",
        "about": "Jeff & Jason & Irene was shit.",
        "tags": ["panda", "dog", "shit"]
      },
      {
        "id": 5,
        "image_url": "https://picsum.photos/400/300/?random=5",
        "title": "test",
        "about": "Jeff & Jason & Irene was shit.",
        "tags": ["panda", "dog", "shit"]
      },
      {
        "id": 6,
        "image_url": "https://picsum.photos/400/300/?random=6",
        "title": "test",
        "about": "Jeff & Jason & Irene was shit.",
        "tags": ["panda", "dog", "shit"]
      },
      {
        "id": 7,
        "image_url": "https://picsum.photos/800/300/?random=7",
        "title": "test",
        "about": "Jeff & Jason & Irene was shit.",
        "tags": ["panda", "dog", "shit"]
      },
      {
        "id": 8,
        "image_url": "https://picsum.photos/400/300/?random=8",
        "title": "test",
        "about": "Jeff & Jason & Irene was shit.",
        "tags": ["panda", "dog", "shit"]
      },
      {
        "id": 9,
        "image_url": "https://picsum.photos/400/300/?random=9",
        "title": "test",
        "about": "Jeff & Jason & Irene was shit.",
        "tags": ["panda", "dog", "shit"]
      }
    ],
  "get_trending":
    [
      {
        "id": 1,
        "image_url": "https://picsum.photos/400/300/?random=1",
        "title": "test",
        "about": "Jeff & Jason & Irene was shit.",
        "tags": ["panda", "dog", "shit"]
      },
      {
        "id": 2,
        "image_url": "https://picsum.photos/400/300/?random=2",
        "title": "test",
        "about": "Jeff & Jason & Irene was shit.",
        "tags": ["panda", "dog", "shit"]
      },
      {
        "id": 3,
        "image_url": "https://picsum.photos/400/300/?random=3",
        "title": "test",
        "about": "Jeff & Jason & Irene was shit.",
        "tags": ["panda", "dog", "shit"]
      },
      {
        "id": 4,
        "image_url": "https://picsum.photos/400/300/?random=4",
        "title": "test",
        "about": "Jeff & Jason & Irene was shit.",
        "tags": ["panda", "dog", "shit"]
      },
      {
        "id": 5,
        "image_url": "https://picsum.photos/400/300/?random=5",
        "title": "test",
        "about": "Jeff & Jason & Irene was shit.",
        "tags": ["panda", "dog", "shit"]
      },
      {
        "id": 6,
        "image_url": "https://picsum.photos/400/300/?random=6",
        "title": "test",
        "about": "Jeff & Jason & Irene was shit.",
        "tags": ["panda", "dog", "shit"]
      },
      {
        "id": 7,
        "image_url": "https://picsum.photos/400/300/?random=7",
        "title": "test",
        "about": "Jeff & Jason & Irene was shit.",
        "tags": ["panda", "dog", "shit"]
      },
      {
        "id": 8,
        "image_url": "https://picsum.photos/400/300/?random=8",
        "title": "test",
        "about": "Jeff & Jason & Irene was shit.",
        "tags": ["panda", "dog", "shit"]
      },
      {
        "id": 9,
        "image_url": "https://picsum.photos/400/300/?random=9",
        "title": "test",
        "about": "Jeff & Jason & Irene was shit.",
        "tags": ["panda", "dog", "shit"]
      }
    ]
}
